arc/__init__.py
arc/autocompletions.py
arc/color.py
arc/config.py
arc/constants.py
arc/define/__init__.py
arc/define/alias.py
arc/define/classful.py
arc/define/command.py
arc/define/documentation.py
arc/define/param/__init__.py
arc/define/param/constructors.py
arc/define/param/groups.py
arc/define/param/param.py
arc/define/param/param_definition.py
arc/define/param/param_instance.py
arc/define/param/param_mixin.py
arc/errors.py
arc/logging.py
arc/parser.py
arc/present/__init__.py
arc/present/_markdown/__init__.py
arc/present/_markdown/_markdown.py
arc/present/_markdown/markdown_parser.py
arc/present/_markdown/nodes.py
arc/present/ansi.py
arc/present/box.py
arc/present/console.py
arc/present/data.py
arc/present/drawing.py
arc/present/formatters.py
arc/present/help_formatter.py
arc/present/joiner.py
arc/present/out.py
arc/present/pager.py
arc/present/table.py
arc/present/wrap.py
arc/prompt/__init__.py
arc/prompt/helpers.py
arc/prompt/prompt.py
arc/prompt/prompts.py
arc/prompt/questions.py
arc/py.typed
arc/runtime/__init__.py
arc/runtime/app.py
arc/runtime/context.py
arc/runtime/exec.py
arc/runtime/init.py
arc/runtime/middleware.py
arc/runtime/plugin.py
arc/safe.py
arc/suggest.py
arc/types/__init__.py
arc/types/aliases.py
arc/types/convert.py
arc/types/dates.py
arc/types/default.py
arc/types/file.py
arc/types/middleware/__init__.py
arc/types/middleware/observers.py
arc/types/middleware/transformers.py
arc/types/middleware/validators.py
arc/types/network.py
arc/types/numbers.py
arc/types/path.py
arc/types/semver.py
arc/types/state.py
arc/types/strings.py
arc/types/type_arg.py
arc/types/type_info.py
arc/types/users.py
arc/typing.py
arc/utils.py
arc/version.py
arc_cli-8.7.1.dist-info/LICENSE
arc_cli-8.7.1.dist-info/METADATA
arc_cli-8.7.1.dist-info/WHEEL
arc_cli-8.7.1.dist-info/RECORD
