Metadata-Version: 2.1
Name: arc-cli
Version: 8.7.1
Summary: Package for creating CLI's with ease.
Home-page: https://github.com/seanrcollings/arc
License: MIT
Author: Sean Collings
Author-email: me@seancollings.dev
Requires-Python: >=3.10,<4.0
Classifier: Intended Audience :: Developers
Classifier: License :: OSI Approved :: MIT License
Classifier: Operating System :: POSIX :: Linux
Classifier: Programming Language :: Python :: 3
Classifier: Programming Language :: Python :: 3.10
Classifier: Programming Language :: Python :: 3.11
Classifier: Programming Language :: Python :: 3.12
Classifier: Typing :: Typed
Project-URL: Documentation, https://arc.seancollings.dev
